pytty/sshshell.py
sshc_py-1.1.dist-info/licenses/LICENSE
sshc_py-1.1.dist-info/METADATA
sshc_py-1.1.dist-info/WHEEL
sshc_py-1.1.dist-info/entry_points.txt
sshc_py-1.1.dist-info/top_level.txt
sshc_py-1.1.dist-info/RECORD
